cosmo_ent/__init__.py
cosmo_ent/__main__.py
cosmo_ent/_version.py
cosmo_ent/data/LICENSE.md
cosmo_ent/data/ent.com
cosmo_ent/data/platform
cosmo_ent-1.4.1.dist-info/licenses/LICENSE
cosmo_ent-1.4.1.dist-info/METADATA
cosmo_ent-1.4.1.dist-info/WHEEL
cosmo_ent-1.4.1.dist-info/entry_points.txt
cosmo_ent-1.4.1.dist-info/top_level.txt
cosmo_ent-1.4.1.dist-info/RECORD
