Metadata-Version: 2.4
Name: cosmo-ent
Version: 1.4.1
Summary: Cosmopolitan builds of ent(1), distributed as a Python package
Author: cosmo-ent contributors
License: MIT License
Project-URL: Homepage, https://github.com/bjia56/cosmo-ent
Project-URL: Repository, https://github.com/bjia56/cosmo-ent
Project-URL: Issues, https://github.com/bjia56/cosmo-ent/issues
Classifier: Development Status :: 4 - Beta
Classifier: Intended Audience :: Developers
Classifier: Intended Audience :: Science/Research
Classifier: License :: OSI Approved :: MIT License
Classifier: Operating System :: OS Independent
Classifier: Programming Language :: Python :: 3
Classifier: Programming Language :: Python :: 3.8
Classifier: Programming Language :: Python :: 3.9
Classifier: Programming Language :: Python :: 3.10
Classifier: Programming Language :: Python :: 3.11
Classifier: Programming Language :: Python :: 3.12
Classifier: Topic :: Scientific/Engineering
Classifier: Topic :: Security :: Cryptography
Classifier: Topic :: Software Development :: Libraries :: Python Modules
Classifier: Topic :: System :: Systems Administration
Requires-Python: >=3.8
License-File: LICENSE
Dynamic: license-file
